Workbook

Sheet Guest Post Sites
A1: Guest Post & Blog Submission Targets - 400 Sites for commonwealthmigration.ca
A2: No. | B2: Website / Blog | C2: Domain | D2: Submission / Guidelines URL | E2: Category | F2: Immigration Relevance | G2: Authority Tier | H2: Authority Metric | I2: Free Submission | J2: Login Required | K2: Captcha Checked | L2: Source | M2: Pitch Angle / Notes
A3: 1 | B3: Arizona State University | C3: asu.edu | D3: https://asu.edu | E3: Education & Study Abroad | F3: High | G3: High | H3: DA 91 / DR 90 | I3: Yes | J3: Unknown | K3: Not tested | L3: CP | M3: University site; institutional contributions.
A4: 2 | B4: Edutopia | C4: edutopia.org | D4: https://www.edutopia.org | E4: Education & Study Abroad | F4: High | G4: High | H4: DA 86 / DR 85 | I4: Yes | J4: Unknown | K4: Not tested | L4: CP | M4: Education innovation.
A5: 3 | B5: ProProfs | C5: proprofs.com | D5: https://www.proprofs.com/c/submit-an-article-on-education/ | E5: Education & Study Abroad | F5: High | G5: High | H5: DA 86 / DR 79 | I5: Yes | J5: No | K5: Not tested | L5: CP | M5: Article submission pages by topic.
A6: 4 | B6: Top Universities | C6: topuniversities.com | D6: https://www.topuniversities.com | E6: Education & Study Abroad | F6: High | G6: High | H6: DA 85 / DR 84 | I6: Yes | J6: Unknown | K6: Not tested | L6: CP | M6: QS study-abroad portal - very strong fit.
A7: 5 | B7: Hostelworld Blog | C7: hostelworld.com | D7: https://www.hostelworld.com | E7: Travel | F7: High | G7: High | H7: DA 84 / DR 81 | I7: Yes | J7: Unknown | K7: Not tested | L7: CP | M7: Global travel brand blog.
A8: 6 | B8: BoardingArea | C8: boardingarea.com | D8: https://boardingarea.com | E8: Travel | F8: High | G8: High | H8: DA 83 / DR 72 | I8: Yes | J8: Unknown | K8: Not tested | L8: CP | M8: Frequent-flyer network; contributors per channel.
A9: 7 | B9: Manning | C9: manning.com | D9: https://www.manning.com | E9: Education & Study Abroad | F9: High | G9: High | H9: DA 71 / DR 83 | I9: Yes | J9: Unknown | K9: Not tested | L9: CP | M9: Publisher contributor programme.
A10: 8 | B10: Above the Law | C10: abovethelaw.com | D10: https://abovethelaw.com | E10: Legal | F10: High | G10: High | H10: DA 81 / DR 79 | I10: Yes | J10: Unknown | K10: Not tested | L10: CP | M10: Legal industry commentary; high authority, selective.
A11: 9 | B11: ASCD | C11: ascd.org | D11: https://www.ascd.org | E11: Education & Study Abroad | F11: High | G11: High | H11: DA 78 / DR 80 | I11: Yes | J11: Unknown | K11: Not tested | L11: CP | M11: Educator association.
A12: 10 | B12: Getting Smart | C12: gettingsmart.com | D12: https://www.gettingsmart.com | E12: Education & Study Abroad | F12: High | G12: High | H12: DA 74 / DR 74 | I12: Yes | J12: Unknown | K12: Not tested | L12: CP | M12: Education innovation.
A13: 11 | B13: International Living | C13: internationalliving.com | D13: https://internationalliving.com/write-for-us/ | E13: Relocation & Expat | F13: High | G13: High | H13: DA 69 / DR 74 | I13: Yes | J13: No | K13: Not tested | L13: CP | M13: Overseas living & retirement abroad; strong topical fit.
A14: 12 | B14: The Planet D | C14: theplanetd.com | D14: https://theplanetd.com | E14: Travel | F14: High | G14: High | H14: DA 69 / DR 73 | I14: Yes | J14: Unknown | K14: Not tested | L14: CP | M14: Major adventure travel blog; guest posts by pitch.
... A402: 400 | B402: Lifestyle Web Blogs | C402: lifestyleweblogs.com | D402: https://lifestyleweblogs.com/lifestyle-write-for-us/ | E402: Lifestyle & General | F402: Medium | G402: Moderate | H402: Not published | I402: Yes | J402: No | K402: Not tested | L402: CJ | M402: 7-10 day review.

Sheet Summary
A1: Summary - 400 guest-post targets for commonwealthmigration.ca
A3: By category
A4: Group | B4: Sites | C4: Share | D4: Notes
A5: Immigration & Visa | B5: =COUNTIF('Guest Post Sites'!$E$3:$E$402,$A5) -> 19 | C5: =IF(OR($B$15="",$B$15=0),"",B5/$B$15) -> 0.0475 | D5: Direct topical match - prioritise these first.
A6: Relocation & Expat | B6: =COUNTIF('Guest Post Sites'!$E$3:$E$402,$A6) -> 24 | C6: =IF(OR($B$15="",$B$15=0),"",B6/$B$15) -> 0.06 | D6: Moving-to-Canada / settling-in content fits naturally.
A7: Travel | B7: =COUNTIF('Guest Post Sites'!$E$3:$E$402,$A7) -> 100 | C7: =IF(OR($B$15="",$B$15=0),"",B7/$B$15) -> 0.25 | D7: Largest pool; use for soft, non-promotional destination & relocation angles.
A8: Legal | B8: =COUNTIF('Guest Post Sites'!$E$3:$E$402,$A8) -> 14 | C8: =IF(OR($B$15="",$B$15=0),"",B8/$B$15) -> 0.035 | D8: YMYL authority; immigration-law explainers land well.
A9: Business & Startup | B9: =COUNTIF('Guest Post Sites'!$E$3:$E$402,$A9) -> 55 | C9: =IF(OR($B$15="",$B$15=0),"",B9/$B$15) -> 0.1375 | D9: Business immigration, investor routes, hiring global talent.
A10: Education & Study Abroad | B10: =COUNTIF('Guest Post Sites'!$E$3:$E$402,$A10) -> 48 | C10: =IF(OR($B$15="",$B$15=0),"",B10/$B$15) -> 0.12 | D10: Study-permit and international-student angles.
A11: Career & HR | B11: =COUNTIF('Guest Post Sites'!$E$3:$E$402,$A11) -> 20 | C11: =IF(OR($B$15="",$B$15=0),"",B11/$B$15) -> 0.05 | D11: Work permits, skilled migration, hiring foreign workers.
A12: Finance & Money | B12: =COUNTIF('Guest Post Sites'!$E$3:$E$402,$A12) -> 30 | C12: =IF(OR($B$15="",$B$15=0),"",B12/$B$15) -> 0.075 | D12: Proof of funds, cost of living, newcomer banking.
A13: Real Estate & Housing | B13: =COUNTIF('Guest Post Sites'!$E$3:$E$402,$A13) -> 21 | C13: =IF(OR($B$15="",$B$15=0),"",B13/$B$15) -> 0.0525 | D13: First home, renting, property for newcomers.
A14: Lifestyle & General | B14: =COUNTIF('Guest Post Sites'!$E$3:$E$402,$A14) -> 69 | C14: =IF(OR($B$15="",$B$15=0),"",B14/$B$15) -> 0.1725 | D14: Broad reach; general-interest and human-interest pieces.
A15: Total | B15: =SUM(B5:B14) -> 400 | C15: =IF(OR(B15="",B15=0),"",SUM(C5:C14)) -> 1
A17: By immigration relevance
A18: Group | B18: Sites | C18: Share | D18: Notes
A19: High | B19: =COUNTIF('Guest Post Sites'!$F$3:$F$402,$A19) -> 225 | C19: =IF(OR($B$21="",$B$21=0),"",B19/$B$21) -> 0.5625 | D19: High = a natural home for immigration / relocation content.
A20: Medium | B20: =COUNTIF('Guest Post Sites'!$F$3:$F$402,$A20) -> 175 | C20: =IF(OR($B$21="",$B$21=0),"",B20/$B$21) -> 0.4375 | D20: Medium = adjacent topic, needs a bridging angle.
A21: Total | B21: =SUM(B19:B20) -> 400 | C21: =IF(OR(B21="",B21=0),"",SUM(C19:C20)) -> 1
A23: By authority tier
A24: Group | B24: Sites | C24: Share | D24: Notes
A25: High | B25: =COUNTIF('Guest Post Sites'!$G$3:$G$402,$A25) -> 112 | C25: =IF(OR($B$27="",$B$27=0),"",B25/$B$27) -> 0.28 | D25: High = DA/DR 60+ or Open PageRank 4.0+, or a well-known publication.
A26: Moderate | B26: =COUNTIF('Guest Post Sites'!$G$3:$G$402,$A26) -> 288 | C26: =IF(OR($B$27="",$B$27=0),"",B26/$B$27) -> 0.72 | D26: Moderate = roughly DA 20-60 / OPR 2.0-4.0. Still worth a link.
A27: Total | B27: =SUM(B25:B26) -> 400 | C27: =IF(OR(B27="",B27=0),"",SUM(C25:C26)) -> 1
A28: Low-relevance and general tech / SaaS candidates were ranked below the top 400 and left out - every site listed is a high or moderate relevance fit.
A29: Submission mechanics
A30: Sites with free submission | B30: =COUNTIF('Guest Post Sites'!$I$3:$I$402,"Yes") -> 392
A31: Sites needing no account / login | B31: =COUNTIF('Guest Post Sites'!$J$3:$J$402,"No") -> 251
A32: Login flow unconfirmed - verify first | B32: =COUNTIF('Guest Post Sites'!$J$3:$J$402,"Unknown") -> 149
A33: Captcha individually tested | B33: Not tested

Sheet Methodology & Caveats
A1: How this list was built - and what it does not claim
A2: Target site | B2: https://commonwealthmigration.ca/ - Canadian immigration / visa consultancy. Content that fits: study permits, work permits, Express Entry, PR pathways, settling in Canada, proof of funds, credential recognition, citizenship.
A3: Compiled | B3: 2026-09-22
A4: Sites listed | B4: 400 - all of them high or moderate relevance to an immigration / relocation audience (225 High, 175 Medium), and all high or moderate authority (112 High, 288 Moderate). Low-relevance and general tech / SaaS candidates were collected but ranked below the cut, because a 400-row list of them would be padding.
A5: Sources | B5: Aggregated from published, crawl-verified guest-post indexes and direct site checks. Source codes in the 'Source' column: MC = MentionAgent crawl - every submission page was actually loaded and read in Aug 2026; paid-placement sites were removed by the publisher. CP = collaborator.pro list (DA and DR published per site). CJ = christopherjanb verified list (submission URL per site). GT = gauravtiwari.org list. PN = prnews.io list. D52 = 52 Perfect Days travel list (DA per site). AX = AAMAX immigration guest-post list. WS = found by direct web search.
A6: Authority | B6: 'Authority Metric' reproduces whatever number the source published - DA (Moz 0-100), DR (Ahrefs 0-100) or OPR (Open PageRank 0-10). 'Authority Tier' is my own High / Moderate banding: High = DA/DR 60+, OPR 4.0+, or a well-known publication; Moderate = roughly DA 20-60 / OPR 2.0-4.0. Where a site publishes no score, the tier reflects its general standing. Treat tiers as a sort order, not a measurement.
A7: IMPORTANT - captcha | B7: I did NOT individually test all 400 sites for captcha or anti-spam challenges, and no automated check in this environment can. The 'Captcha Checked' column therefore reads 'Not tested' throughout. Nearly every WordPress contact form ships with some spam filtering, so assume a checkbox or invisible challenge on form-based submissions. Where a site offers an editorial email address, pitch by email instead - that route has no captcha at all.
A8: IMPORTANT - login | B8: 'Login Required' = No means the source shows a plain form or email address, with no account needed. 'Unknown' means the source did not make the flow explicit - verify before you write. Sites known to require an account to submit (DZone, Slashdot, HackerNoon, iTechCode and similar) were ranked out of the top 400 and do not appear.
A9: Free submission | B9: Yes = no fee was stated at the source. A handful of sites pay contributors instead (flagged in the notes) and three are marked No because they charge. Note: sites that openly sell placements were already stripped out of the MC-sourced rows by the original publisher.
A10: Verification gap | B10: Only the MC-sourced rows (source code MC) come from a crawl that loaded and read each submission page. CP / CJ / GT / PN / D52 / AX rows come from third-party lists and were not re-crawled here. Before writing, open the submission URL and confirm it is still live - guest-post programmes close quietly and often.
A11: How to use it | B11: 1. Sort or filter 'Immigration Relevance' = High and work down that list first. 2. Within a relevance band, the sheet is already sorted by authority (strongest first). 3. Read the site's own guidelines page before pitching - word count, link rules and whether a company name is allowed in the headline vary a lot. 4. Pitch a specific article, not a topic area, and reference something the site already published.
A12: Column glossary | B12: Submission / Guidelines URL = the page that tells you how to submit (or the site root where no dedicated page exists). Pitch Angle / Notes = what to lead with, plus any stated constraint (word count, link limits, fee, payment). Source = where the row came from; MC rows are the most recently verified.
A13: Deliberate exclusions | B13: Sites that sell placements outright, sites whose submission page 404s or bounces to the homepage, and sites requiring an account to submit were excluded - with the single flagged exception noted above. A few rows are reference-only (government sites, low-relevance fillers) and are labelled as such in the notes.
